Mx/DHT.py
Mx/MPipe.py
Mx/PCF8591.py
Mx/SArduino.py
Mx/Servo.py
Mx/__init__.py
Mx/audio_classifier.py
Mx/audio_classifier_test.py
Mx/audio_classify.py
Mx/audio_record.py
Mx/classifier.py
Mx/hcsr04.py
Mx/image.py
Mx/mxopencv.py
Mx/oleds.py
Mx/pyqtgraph_line.py
Mx/sound.py
Mx/utils.py
Mx/xgolib.py
Mx/yolo_fast.py
Mx/Soundcls/__init__.py
Mx/Soundcls/create_data.py
Mx/Soundcls/__pycache__/__init__.cpython-310.pyc
Mx/Soundcls/__pycache__/create_data.cpython-310.pyc
Mx/Soundcls/__pycache__/infer.cpython-310.pyc
Mx/Soundcls/configs/augmentation.json
Mx/Soundcls/configs/ecapa_tdnn.yml
Mx/Soundcls/configs/panns.yml
Mx/Soundcls/macls/__init__.py
Mx/Soundcls/macls/predict.py
Mx/Soundcls/macls/trainer.py
Mx/Soundcls/macls/__pycache__/__init__.cpython-310.pyc
Mx/Soundcls/macls/__pycache__/predict.cpython-310.pyc
Mx/Soundcls/macls/__pycache__/trainer.cpython-310.pyc
Mx/Soundcls/macls/data_utils/__init__.py
Mx/Soundcls/macls/data_utils/audio.py
Mx/Soundcls/macls/data_utils/featurizer.py
Mx/Soundcls/macls/data_utils/reader.py
Mx/Soundcls/macls/data_utils/utils.py
Mx/Soundcls/macls/data_utils/__pycache__/__init__.cpython-310.pyc
Mx/Soundcls/macls/data_utils/__pycache__/audio.cpython-310.pyc
Mx/Soundcls/macls/data_utils/__pycache__/featurizer.cpython-310.pyc
Mx/Soundcls/macls/data_utils/__pycache__/reader.cpython-310.pyc
Mx/Soundcls/macls/data_utils/__pycache__/utils.cpython-310.pyc
Mx/Soundcls/macls/data_utils/augmentor/__init__.py
Mx/Soundcls/macls/data_utils/augmentor/augmentation.py
Mx/Soundcls/macls/data_utils/augmentor/base.py
Mx/Soundcls/macls/data_utils/augmentor/noise_perturb.py
Mx/Soundcls/macls/data_utils/augmentor/resample.py
Mx/Soundcls/macls/data_utils/augmentor/shift_perturb.py
Mx/Soundcls/macls/data_utils/augmentor/spec_augment.py
Mx/Soundcls/macls/data_utils/augmentor/spec_sub.py
Mx/Soundcls/macls/data_utils/augmentor/speed_perturb.py
Mx/Soundcls/macls/data_utils/augmentor/volume_perturb.py
Mx/Soundcls/macls/data_utils/augmentor/__pycache__/__init__.cpython-310.pyc
mxpi_mx-1.4.5.dist-info/METADATA
mxpi_mx-1.4.5.dist-info/WHEEL
mxpi_mx-1.4.5.dist-info/top_level.txt
mxpi_mx-1.4.5.dist-info/RECORD
