Metadata-Version: 2.1
Name: mxpi-mx
Version: 1.4.5
Summary: mxpi-mx
Home-page: https://github.com/yuanyunqiang/
Author: YuanYunQiang
Author-email: 649756903@qq.com
License: MIT Licence
Keywords: pip,SICA,featureextraction
Platform: any
